MANIFEST.in
README.txt
setup.py
mlboost/__init__.py
mlboost.egg-info/PKG-INFO
mlboost.egg-info/SOURCES.txt
mlboost.egg-info/dependency_links.txt
mlboost.egg-info/requires.txt
mlboost.egg-info/top_level.txt
mlboost/core/__init__.py
mlboost/core/ppcorr.py
mlboost/core/ppdataset.py
mlboost/core/ppdist.py
mlboost/core/pphisto.py
mlboost/core/pputil.py
mlboost/core/pylabhisto.py
mlboost/image/__init__.py
mlboost/image/util.py
mlboost/nn/__init__.py
mlboost/nn/nn.py
mlboost/nn/optnn.py