Metadata-Version: 1.0
Name: mlboost
Version: 0.4.1
Summary: an innovative machine learning library for extreme prototyping
Home-page: http://sourceforge.net/projects/mlboost/
Author: Francis Pieraut
Author-email: fpieraut@gmail.com
License: AGPL v3 or later
Platform: UNKNOWN
